bmbix_sdk/__init__.py
bmbix_sdk/api.py
bmbix_sdk/util.py
bmbix_sdk/version.py
bmbix_sdk/documents/__init__.py
bmbix_sdk/documents/bmbix_5/__init__.py
bmbix_sdk/documents/bmbix_5/invoice.py
bmbix_sdk/documents/ubl_2_2/__init__.py
bmbix_sdk/documents/ubl_2_2/invoice.py
bmbix_sdk-0.0.18.dist-info/LICENCE
bmbix_sdk-0.0.18.dist-info/METADATA
bmbix_sdk-0.0.18.dist-info/WHEEL
bmbix_sdk-0.0.18.dist-info/top_level.txt
bmbix_sdk-0.0.18.dist-info/RECORD
