Metadata-Version: 2.1
Name: bmbix-sdk
Version: 0.0.18
Summary: Bmbix SDK
Home-page: https://gitlab.com/bmbix/bmbix-sdk-python
Author: Robin Abbi
Author-email: robin.abbi@bmbix.com
License: Apache
Keywords: Bmbix,SDK
Platform: UNKNOWN
License-File: LICENCE
Requires-Dist: attrs
Requires-Dist: cryptography
Requires-Dist: dateparser
Requires-Dist: lxml
Requires-Dist: oauthlib
Requires-Dist: requests-oauthlib
Requires-Dist: pycryptodome
Requires-Dist: bmb-klondike-client
Requires-Dist: bmb-martlet-organization-client
Provides-Extra: tests
Requires-Dist: pytest ; extra == 'tests'
